UNSC_Sanctions_Checker.py
unsc_sanctions_checker/__init__.py
unsc_sanctions_checker/__main__.py
unsc_sanctions_checker/data/__init__.py
unsc_sanctions_checker/data/consolidated.xml
unsc_sanctions_checker/template/__init__.py
unsc_sanctions_checker/template/report.html
unsc_sanctions_checker/wkhtmltopdf/__init__.py
unsc_sanctions_checker/wkhtmltopdf/wkhtmltopdf.exe
unsc_sanctions_checker-3.1.1.dist-info/LICENSE
unsc_sanctions_checker-3.1.1.dist-info/METADATA
unsc_sanctions_checker-3.1.1.dist-info/WHEEL
unsc_sanctions_checker-3.1.1.dist-info/entry_points.txt
unsc_sanctions_checker-3.1.1.dist-info/top_level.txt
unsc_sanctions_checker-3.1.1.dist-info/RECORD
