Metadata-Version: 2.1
Name: unsc-sanctions-checker
Version: 3.1.1
Summary: UNSC Sanctions checker with a GUI
Home-page: https://github.com/Lcrs123/UNSC_Sanctions_Checker
Author: Lucas Camillo
Author-email: lucascamillo333@hotmail.com
License: GNU
Platform: UNKNOWN
Classifier: Programming Language :: Python :: 3
Classifier: Development Status :: 4 - Beta
Classifier: License :: OSI Approved :: GNU General Public License v3 (GPLv3)
Classifier: Operating System :: Microsoft :: Windows
Requires-Python: >=3.7
Requires-Dist: pdfkit
Requires-Dist: jinja2
Requires-Dist: fuzzywuzzy
Requires-Dist: requests
Requires-Dist: pandas
